[{"message_id": 10, "channel_id": 779202598, "u_id": 360507476, "message": "Our team is the winner.", "time_created": 1603442103}, {"message_id": 9, "channel_id": 779202598, "u_id": 360507476, "message": "I am pretty sure about that", "time_created": 1603442103}, {"message_id": 8, "channel_id": 779202598, "u_id": 360507476, "message": "the winner.", "time_created": 1603442103}, {"message_id": 7, "channel_id": 779202598, "u_id": 360507476, "message": "I heard he is the winner", "time_created": 1603442103}, {"message_id": 6, "channel_id": 779202598, "u_id": 360507476, "message": "We are the winner.", "time_created": 1603442103}, {"message_id": 5, "channel_id": 2806952002, "u_id": 3446735043, "message": "Tomorrow, I will be the winner.", "time_created": 1603442103}, {"message_id": 4, "channel_id": 2806952002, "u_id": 3446735043, "message": "Cool!", "time_created": 1603442103}, {"message_id": 3, "channel_id": 2806952002, "u_id": 3446735043, "message": "Yesterday, I was the winner.", "time_created": 1603442103}, {"message_id": 2, "channel_id": 2806952002, "u_id": 3446735043, "message": "What about you?", "time_created": 1603442103}, {"message_id": 1, "channel_id": 2806952002, "u_id": 3446735043, "message": "Today, I am the winner.", "time_created": 1603442103}]